[
  {
    "id": 1,
    "ability_id": 1,
    "obtain_id": 1,
    "type_id": 1,
    "speed_id": 5,
    "size_id": 1,
    "temperature_id": 2,
    "ph_id": 2,
    "slug": "kurikin",
    "img": "https://raw.githubusercontent.com/takuyadev/kuriapi/main/assets/kin/face_sprite/kin_1.png",
    "hp": 76,
    "attack": 53,
    "defense": 11,
    "attack_speed": 67,
    "growth_speed": 236
  },
  {
    "id": 2,
    "ability_id": 3,
    "obtain_id": 1,
    "type_id": 3,
    "speed_id": 5,
    "size_id": 1,
    "temperature_id": 1,
    "ph_id": 1,
    "slug": "kabirusu",
    "img": "https://raw.githubusercontent.com/takuyadev/kuriapi/main/assets/kin/face_sprite/kin_2.png",
    "hp": 77,
    "attack": 52,
    "defense": 1,
    "attack_speed": 62,
    "growth_speed": 220
  },
  {
    "id": 3,
    "ability_id": 2,
    "obtain_id": 1,
    "type_id": 2,
    "speed_id": 5,
    "size_id": 2,
    "temperature_id": 1,
    "ph_id": 1,
    "slug": "gomisukin",
    "img": "https://raw.githubusercontent.com/takuyadev/kuriapi/main/assets/kin/face_sprite/kin_3.png",
    "hp": 146,
    "attack": 140,
    "defense": 21,
    "attack_speed": 45,
    "growth_speed": 125
  },
  {
    "id": 4,
    "ability_id": 1,
    "obtain_id": 1,
    "type_id": 1,
    "speed_id": 5,
    "size_id": 2,
    "temperature_id": 3,
    "ph_id": 1,
    "slug": "burigokin",
    "img": "https://raw.githubusercontent.com/takuyadev/kuriapi/main/assets/kin/face_sprite/kin_4.png",
    "hp": 92,
    "attack": 195,
    "defense": 1,
    "attack_speed": 247,
    "growth_speed": 238
  },
  {
    "id": 5,
    "ability_id": 3,
    "obtain_id": 1,
    "type_id": 3,
    "speed_id": 5,
    "size_id": 1,
    "temperature_id": 3,
    "ph_id": 2,
    "slug": "demekin",
    "img": "https://raw.githubusercontent.com/takuyadev/kuriapi/main/assets/kin/face_sprite/kin_5.png",
    "hp": 76,
    "attack": 53,
    "defense": 31,
    "attack_speed": 82,
    "growth_speed": 233
  },
  {
    "id": 6,
    "ability_id": 1,
    "obtain_id": 1,
    "type_id": 1,
    "speed_id": 5,
    "size_id": 1,
    "temperature_id": 3,
    "ph_id": 1,
    "slug": "erekin",
    "img": "https://raw.githubusercontent.com/takuyadev/kuriapi/main/assets/kin/face_sprite/kin_6.png",
    "hp": 74,
    "attack": 55,
    "defense": 24,
    "attack_speed": 77,
    "growth_speed": 235
  },
  {
    "id": 7,
    "ability_id": 3,
    "obtain_id": 1,
    "type_id": 3,
    "speed_id": 5,
    "size_id": 1,
    "temperature_id": 3,
    "ph_id": 1,
    "slug": "hatoria",
    "img": "https://raw.githubusercontent.com/takuyadev/kuriapi/main/assets/kin/face_sprite/kin_7.png",
    "hp": 74,
    "attack": 55,
    "defense": 15,
    "attack_speed": 72,
    "growth_speed": 235
  },
  {
    "id": 8,
    "ability_id": 3,
    "obtain_id": 1,
    "type_id": 3,
    "speed_id": 5,
    "size_id": 2,
    "temperature_id": 3,
    "ph_id": 1,
    "slug": "merodiumu",
    "img": "https://raw.githubusercontent.com/takuyadev/kuriapi/main/assets/kin/face_sprite/kin_8.png",
    "hp": 152,
    "attack": 135,
    "defense": 12,
    "attack_speed": 45,
    "growth_speed": 128
  },
  {
    "id": 9,
    "ability_id": 2,
    "obtain_id": 1,
    "type_id": 2,
    "speed_id": 5,
    "size_id": 1,
    "temperature_id": 2,
    "ph_id": 1,
    "slug": "toraia",
    "img": "https://raw.githubusercontent.com/takuyadev/kuriapi/main/assets/kin/face_sprite/kin_9.png",
    "hp": 74,
    "attack": 55,
    "defense": 1,
    "attack_speed": 62,
    "growth_speed": 212
  },
  {
    "id": 10,
    "ability_id": 1,
    "obtain_id": 1,
    "type_id": 1,
    "speed_id": 5,
    "size_id": 1,
    "temperature_id": 3,
    "ph_id": 1,
    "slug": "kibarin",
    "img": "https://raw.githubusercontent.com/takuyadev/kuriapi/main/assets/kin/face_sprite/kin_10.png",
    "hp": 77,
    "attack": 52,
    "defense": 7,
    "attack_speed": 62,
    "growth_speed": 212
  },
  {
    "id": 11,
    "ability_id": 2,
    "obtain_id": 1,
    "type_id": 2,
    "speed_id": 5,
    "size_id": 2,
    "temperature_id": 3,
    "ph_id": 1,
    "slug": "kagamin",
    "img": "https://raw.githubusercontent.com/takuyadev/kuriapi/main/assets/kin/face_sprite/kin_11.png",
    "hp": 146,
    "attack": 140,
    "defense": 18,
    "attack_speed": 50,
    "growth_speed": 122
  },
  {
    "id": 12,
    "ability_id": 2,
    "obtain_id": 1,
    "type_id": 2,
    "speed_id": 5,
    "size_id": 1,
    "temperature_id": 3,
    "ph_id": 1,
    "slug": "sarakin",
    "img": "https://raw.githubusercontent.com/takuyadev/kuriapi/main/assets/kin/face_sprite/kin_12.png",
    "hp": 74,
    "attack": 55,
    "defense": 1,
    "attack_speed": 72,
    "growth_speed": 236
  },
  {
    "id": 13,
    "ability_id": 2,
    "obtain_id": 1,
    "type_id": 2,
    "speed_id": 5,
    "size_id": 1,
    "temperature_id": 2,
    "ph_id": 1,
    "slug": "azukin",
    "img": "https://raw.githubusercontent.com/takuyadev/kuriapi/main/assets/kin/face_sprite/kin_13.png",
    "hp": 52,
    "attack": 77,
    "defense": 19,
    "attack_speed": 92,
    "growth_speed": 240
  },
  {
    "id": 14,
    "ability_id": 1,
    "obtain_id": 1,
    "type_id": 1,
    "speed_id": 5,
    "size_id": 1,
    "temperature_id": 1,
    "ph_id": 1,
    "slug": "usakin",
    "img": "https://raw.githubusercontent.com/takuyadev/kuriapi/main/assets/kin/face_sprite/kin_14.png",
    "hp": 77,
    "attack": 52,
    "defense": 13,
    "attack_speed": 67,
    "growth_speed": 214
  },
  {
    "id": 15,
    "ability_id": 1,
    "obtain_id": 1,
    "type_id": 1,
    "speed_id": 5,
    "size_id": 1,
    "temperature_id": 2,
    "ph_id": 2,
    "slug": "chibirusu",
    "img": "https://raw.githubusercontent.com/takuyadev/kuriapi/main/assets/kin/face_sprite/kin_15.png",
    "hp": 76,
    "attack": 53,
    "defense": 13,
    "attack_speed": 67,
    "growth_speed": 215
  },
  {
    "id": 16,
    "ability_id": 3,
    "obtain_id": 1,
    "type_id": 3,
    "speed_id": 5,
    "size_id": 1,
    "temperature_id": 2,
    "ph_id": 1,
    "slug": "benjerato",
    "img": "https://raw.githubusercontent.com/takuyadev/kuriapi/main/assets/kin/face_sprite/kin_16.png",
    "hp": 79,
    "attack": 50,
    "defense": 31,
    "attack_speed": 72,
    "growth_speed": 215
  },
  {
    "id": 17,
    "ability_id": 3,
    "obtain_id": 1,
    "type_id": 3,
    "speed_id": 5,
    "size_id": 1,
    "temperature_id": 3,
    "ph_id": 2,
    "slug": "hanakin",
    "img": "https://raw.githubusercontent.com/takuyadev/kuriapi/main/assets/kin/face_sprite/kin_17.png",
    "hp": 80,
    "attack": 49,
    "defense": 3,
    "attack_speed": 82,
    "growth_speed": 220
  },
  {
    "id": 18,
    "ability_id": 2,
    "obtain_id": 1,
    "type_id": 2,
    "speed_id": 5,
    "size_id": 1,
    "temperature_id": 2,
    "ph_id": 1,
    "slug": "panpukin",
    "img": "https://raw.githubusercontent.com/takuyadev/kuriapi/main/assets/kin/face_sprite/kin_18.png",
    "hp": 75,
    "attack": 54,
    "defense": 17,
    "attack_speed": 72,
    "growth_speed": 225
  },
  {
    "id": 19,
    "ability_id": 2,
    "obtain_id": 1,
    "type_id": 2,
    "speed_id": 5,
    "size_id": 1,
    "temperature_id": 2,
    "ph_id": 2,
    "slug": "amakuchin",
    "img": "https://raw.githubusercontent.com/takuyadev/kuriapi/main/assets/kin/face_sprite/kin_19.png",
    "hp": 77,
    "attack": 52,
    "defense": 26,
    "attack_speed": 77,
    "growth_speed": 215
  },
  {
    "id": 20,
    "ability_id": 3,
    "obtain_id": 1,
    "type_id": 3,
    "speed_id": 5,
    "size_id": 1,
    "temperature_id": 1,
    "ph_id": 1,
    "slug": "chakin",
    "img": "https://raw.githubusercontent.com/takuyadev/kuriapi/main/assets/kin/face_sprite/kin_20.png",
    "hp": 77,
    "attack": 52,
    "defense": 29,
    "attack_speed": 77,
    "growth_speed": 235
  },
  {
    "id": 21,
    "ability_id": 2,
    "obtain_id": 1,
    "type_id": 2,
    "speed_id": 5,
    "size_id": 1,
    "temperature_id": 1,
    "ph_id": 1,
    "slug": "hekusaria",
    "img": "https://raw.githubusercontent.com/takuyadev/kuriapi/main/assets/kin/face_sprite/kin_21.png",
    "hp": 76,
    "attack": 53,
    "defense": 35,
    "attack_speed": 72,
    "growth_speed": 212
  },
  {
    "id": 22,
    "ability_id": 1,
    "obtain_id": 1,
    "type_id": 1,
    "speed_id": 3,
    "size_id": 3,
    "temperature_id": 1,
    "ph_id": 1,
    "slug": "onionis",
    "img": "https://raw.githubusercontent.com/takuyadev/kuriapi/main/assets/kin/face_sprite/kin_22.png",
    "hp": 213,
    "attack": 231,
    "defense": 2,
    "attack_speed": 15,
    "growth_speed": 69
  },
  {
    "id": 23,
    "ability_id": 1,
    "obtain_id": 1,
    "type_id": 1,
    "speed_id": 5,
    "size_id": 2,
    "temperature_id": 3,
    "ph_id": 1,
    "slug": "kabukkin",
    "img": "https://raw.githubusercontent.com/takuyadev/kuriapi/main/assets/kin/face_sprite/kin_23.png",
    "hp": 152,
    "attack": 135,
    "defense": 12,
    "attack_speed": 35,
    "growth_speed": 127
  },
  {
    "id": 24,
    "ability_id": 3,
    "obtain_id": 1,
    "type_id": 3,
    "speed_id": 5,
    "size_id": 1,
    "temperature_id": 1,
    "ph_id": 2,
    "slug": "penkin",
    "img": "https://raw.githubusercontent.com/takuyadev/kuriapi/main/assets/kin/face_sprite/kin_24.png",
    "hp": 76,
    "attack": 53,
    "defense": 2,
    "attack_speed": 82,
    "growth_speed": 220
  },
  {
    "id": 25,
    "ability_id": 1,
    "obtain_id": 1,
    "type_id": 1,
    "speed_id": 5,
    "size_id": 1,
    "temperature_id": 2,
    "ph_id": 1,
    "slug": "sameba",
    "img": "https://raw.githubusercontent.com/takuyadev/kuriapi/main/assets/kin/face_sprite/kin_25.png",
    "hp": 79,
    "attack": 50,
    "defense": 1,
    "attack_speed": 62,
    "growth_speed": 222
  },
  {
    "id": 26,
    "ability_id": 3,
    "obtain_id": 1,
    "type_id": 3,
    "speed_id": 5,
    "size_id": 2,
    "temperature_id": 1,
    "ph_id": 1,
    "slug": "baundorufin",
    "img": "https://raw.githubusercontent.com/takuyadev/kuriapi/main/assets/kin/face_sprite/kin_26.png",
    "hp": 149,
    "attack": 138,
    "defense": 2,
    "attack_speed": 35,
    "growth_speed": 131
  },
  {
    "id": 27,
    "ability_id": 1,
    "obtain_id": 1,
    "type_id": 1,
    "speed_id": 5,
    "size_id": 1,
    "temperature_id": 3,
    "ph_id": 1,
    "slug": "karakuchin",
    "img": "https://raw.githubusercontent.com/takuyadev/kuriapi/main/assets/kin/face_sprite/kin_27.png",
    "hp": 75,
    "attack": 54,
    "defense": 27,
    "attack_speed": 77,
    "growth_speed": 224
  },
  {
    "id": 28,
    "ability_id": 3,
    "obtain_id": 1,
    "type_id": 3,
    "speed_id": 3,
    "size_id": 3,
    "temperature_id": 1,
    "ph_id": 1,
    "slug": "kinguzori",
    "img": "https://raw.githubusercontent.com/takuyadev/kuriapi/main/assets/kin/face_sprite/kin_28.png",
    "hp": 218,
    "attack": 227,
    "defense": 16,
    "attack_speed": 13,
    "growth_speed": 51
  },
  {
    "id": 29,
    "ability_id": 1,
    "obtain_id": 1,
    "type_id": 1,
    "speed_id": 5,
    "size_id": 2,
    "temperature_id": 1,
    "ph_id": 2,
    "slug": "kiramekin",
    "img": "https://raw.githubusercontent.com/takuyadev/kuriapi/main/assets/kin/face_sprite/kin_29.png",
    "hp": 100,
    "attack": 186,
    "defense": 10,
    "attack_speed": 52,
    "growth_speed": 156
  },
  {
    "id": 30,
    "ability_id": 3,
    "obtain_id": 1,
    "type_id": 3,
    "speed_id": 5,
    "size_id": 1,
    "temperature_id": 3,
    "ph_id": 2,
    "slug": "kindaku",
    "img": "https://raw.githubusercontent.com/takuyadev/kuriapi/main/assets/kin/face_sprite/kin_30.png",
    "hp": 74,
    "attack": 55,
    "defense": 31,
    "attack_speed": 82,
    "growth_speed": 225
  },
  {
    "id": 31,
    "ability_id": 1,
    "obtain_id": 1,
    "type_id": 1,
    "speed_id": 5,
    "size_id": 2,
    "temperature_id": 1,
    "ph_id": 2,
    "slug": "sabokin",
    "img": "https://raw.githubusercontent.com/takuyadev/kuriapi/main/assets/kin/face_sprite/kin_31.png",
    "hp": 152,
    "attack": 135,
    "defense": 12,
    "attack_speed": 45,
    "growth_speed": 125
  },
  {
    "id": 32,
    "ability_id": 3,
    "obtain_id": 1,
    "type_id": 3,
    "speed_id": 5,
    "size_id": 1,
    "temperature_id": 2,
    "ph_id": 1,
    "slug": "kinburera",
    "img": "https://raw.githubusercontent.com/takuyadev/kuriapi/main/assets/kin/face_sprite/kin_32.png",
    "hp": 75,
    "attack": 54,
    "defense": 31,
    "attack_speed": 82,
    "growth_speed": 215
  },
  {
    "id": 33,
    "ability_id": 2,
    "obtain_id": 1,
    "type_id": 2,
    "speed_id": 5,
    "size_id": 2,
    "temperature_id": 3,
    "ph_id": 1,
    "slug": "tamamoguran",
    "img": "https://raw.githubusercontent.com/takuyadev/kuriapi/main/assets/kin/face_sprite/kin_33.png",
    "hp": 149,
    "attack": 138,
    "defense": 16,
    "attack_speed": 50,
    "growth_speed": 125
  },
  {
    "id": 34,
    "ability_id": 3,
    "obtain_id": 1,
    "type_id": 3,
    "speed_id": 5,
    "size_id": 2,
    "temperature_id": 3,
    "ph_id": 2,
    "slug": "meidokin",
    "img": "https://raw.githubusercontent.com/takuyadev/kuriapi/main/assets/kin/face_sprite/kin_34.png",
    "hp": 149,
    "attack": 138,
    "defense": 21,
    "attack_speed": 45,
    "growth_speed": 120
  },
  {
    "id": 35,
    "ability_id": 3,
    "obtain_id": 1,
    "type_id": 3,
    "speed_id": 4,
    "size_id": 2,
    "temperature_id": 2,
    "ph_id": 2,
    "slug": "zoukin",
    "img": "https://raw.githubusercontent.com/takuyadev/kuriapi/main/assets/kin/face_sprite/kin_35.png",
    "hp": 120,
    "attack": 166,
    "defense": 24,
    "attack_speed": 27,
    "growth_speed": 114
  },
  {
    "id": 36,
    "ability_id": 2,
    "obtain_id": 1,
    "type_id": 2,
    "speed_id": 5,
    "size_id": 1,
    "temperature_id": 2,
    "ph_id": 1,
    "slug": "hemogurokin",
    "img": "https://raw.githubusercontent.com/takuyadev/kuriapi/main/assets/kin/face_sprite/kin_36.png",
    "hp": 75,
    "attack": 54,
    "defense": 19,
    "attack_speed": 82,
    "growth_speed": 234
  },
  {
    "id": 37,
    "ability_id": 5,
    "obtain_id": 1,
    "type_id": 2,
    "speed_id": 5,
    "size_id": 2,
    "temperature_id": 2,
    "ph_id": 1,
    "slug": "kyanderia",
    "img": "https://raw.githubusercontent.com/takuyadev/kuriapi/main/assets/kin/face_sprite/kin_37.png",
    "hp": 149,
    "attack": 138,
    "defense": 20,
    "attack_speed": 55,
    "growth_speed": 124
  },
  {
    "id": 38,
    "ability_id": 2,
    "obtain_id": 1,
    "type_id": 2,
    "speed_id": 4,
    "size_id": 1,
    "temperature_id": 1,
    "ph_id": 1,
    "slug": "randoru",
    "img": "https://raw.githubusercontent.com/takuyadev/kuriapi/main/assets/kin/face_sprite/kin_38.png",
    "hp": 26,
    "attack": 103,
    "defense": 2,
    "attack_speed": 192,
    "growth_speed": 230
  },
  {
    "id": 39,
    "ability_id": 2,
    "obtain_id": 1,
    "type_id": 2,
    "speed_id": 3,
    "size_id": 3,
    "temperature_id": 3,
    "ph_id": 2,
    "slug": "kurosuwamu",
    "img": "https://raw.githubusercontent.com/takuyadev/kuriapi/main/assets/kin/face_sprite/kin_39.png",
    "hp": 311,
    "attack": 133,
    "defense": 20,
    "attack_speed": 24,
    "growth_speed": 35
  },
  {
    "id": 40,
    "ability_id": 4,
    "obtain_id": 1,
    "type_id": 2,
    "speed_id": 5,
    "size_id": 2,
    "temperature_id": 3,
    "ph_id": 2,
    "slug": "benian",
    "img": "https://raw.githubusercontent.com/takuyadev/kuriapi/main/assets/kin/face_sprite/kin_40.png",
    "hp": 149,
    "attack": 138,
    "defense": 16,
    "attack_speed": 40,
    "growth_speed": 124
  },
  {
    "id": 41,
    "ability_id": 1,
    "obtain_id": 1,
    "type_id": 1,
    "speed_id": 5,
    "size_id": 1,
    "temperature_id": 1,
    "ph_id": 1,
    "slug": "shurikin",
    "img": "https://raw.githubusercontent.com/takuyadev/kuriapi/main/assets/kin/face_sprite/kin_41.png",
    "hp": 52,
    "attack": 77,
    "defense": 32,
    "attack_speed": 57,
    "growth_speed": 209
  },
  {
    "id": 42,
    "ability_id": 2,
    "obtain_id": 1,
    "type_id": 2,
    "speed_id": 5,
    "size_id": 2,
    "temperature_id": 1,
    "ph_id": 1,
    "slug": "kawarari",
    "img": "https://raw.githubusercontent.com/takuyadev/kuriapi/main/assets/kin/face_sprite/kin_42.png",
    "hp": 149,
    "attack": 138,
    "defense": 21,
    "attack_speed": 55,
    "growth_speed": 140
  },
  {
    "id": 43,
    "ability_id": 4,
    "obtain_id": 1,
    "type_id": 3,
    "speed_id": 5,
    "size_id": 2,
    "temperature_id": 2,
    "ph_id": 1,
    "slug": "gourikin",
    "img": "https://raw.githubusercontent.com/takuyadev/kuriapi/main/assets/kin/face_sprite/kin_43.png",
    "hp": 92,
    "attack": 195,
    "defense": 21,
    "attack_speed": 35,
    "growth_speed": 125
  },
  {
    "id": 44,
    "ability_id": 1,
    "obtain_id": 1,
    "type_id": 1,
    "speed_id": 5,
    "size_id": 2,
    "temperature_id": 3,
    "ph_id": 1,
    "slug": "majoriumu",
    "img": "https://raw.githubusercontent.com/takuyadev/kuriapi/main/assets/kin/face_sprite/kin_44.png",
    "hp": 146,
    "attack": 140,
    "defense": 20,
    "attack_speed": 55,
    "growth_speed": 130
  },
  {
    "id": 45,
    "ability_id": 2,
    "obtain_id": 1,
    "type_id": 2,
    "speed_id": 5,
    "size_id": 1,
    "temperature_id": 1,
    "ph_id": 1,
    "slug": "pareton",
    "img": "https://raw.githubusercontent.com/takuyadev/kuriapi/main/assets/kin/face_sprite/kin_45.png",
    "hp": 77,
    "attack": 52,
    "defense": 18,
    "attack_speed": 72,
    "growth_speed": 215
  },
  {
    "id": 46,
    "ability_id": 3,
    "obtain_id": 1,
    "type_id": 3,
    "speed_id": 5,
    "size_id": 2,
    "temperature_id": 1,
    "ph_id": 1,
    "slug": "burasshi",
    "img": "https://raw.githubusercontent.com/takuyadev/kuriapi/main/assets/kin/face_sprite/kin_46.png",
    "hp": 149,
    "attack": 138,
    "defense": 5,
    "attack_speed": 45,
    "growth_speed": 140
  },
  {
    "id": 47,
    "ability_id": 4,
    "obtain_id": 1,
    "type_id": 3,
    "speed_id": 5,
    "size_id": 2,
    "temperature_id": 1,
    "ph_id": 1,
    "slug": "marione",
    "img": "https://raw.githubusercontent.com/takuyadev/kuriapi/main/assets/kin/face_sprite/kin_47.png",
    "hp": 152,
    "attack": 135,
    "defense": 9,
    "attack_speed": 50,
    "growth_speed": 140
  },
  {
    "id": 48,
    "ability_id": 3,
    "obtain_id": 1,
    "type_id": 3,
    "speed_id": 5,
    "size_id": 2,
    "temperature_id": 3,
    "ph_id": 2,
    "slug": "nigamin",
    "img": "https://raw.githubusercontent.com/takuyadev/kuriapi/main/assets/kin/face_sprite/kin_48.png",
    "hp": 149,
    "attack": 138,
    "defense": 8,
    "attack_speed": 40,
    "growth_speed": 130
  },
  {
    "id": 49,
    "ability_id": 1,
    "obtain_id": 1,
    "type_id": 1,
    "speed_id": 5,
    "size_id": 1,
    "temperature_id": 1,
    "ph_id": 2,
    "slug": "piguria",
    "img": "https://raw.githubusercontent.com/takuyadev/kuriapi/main/assets/kin/face_sprite/kin_49.png",
    "hp": 74,
    "attack": 55,
    "defense": 11,
    "attack_speed": 67,
    "growth_speed": 220
  },
  {
    "id": 50,
    "ability_id": 3,
    "obtain_id": 1,
    "type_id": 3,
    "speed_id": 5,
    "size_id": 1,
    "temperature_id": 3,
    "ph_id": 2,
    "slug": "rifion",
    "img": "https://raw.githubusercontent.com/takuyadev/kuriapi/main/assets/kin/face_sprite/kin_50.png",
    "hp": 80,
    "attack": 49,
    "defense": 41,
    "attack_speed": 67,
    "growth_speed": 210
  },
  {
    "id": 51,
    "ability_id": 2,
    "obtain_id": 1,
    "type_id": 2,
    "speed_id": 1,
    "size_id": 3,
    "temperature_id": 1,
    "ph_id": 2,
    "slug": "bibiriumu",
    "img": "https://raw.githubusercontent.com/takuyadev/kuriapi/main/assets/kin/face_sprite/kin_51.png",
    "hp": 89,
    "attack": 355,
    "defense": 3,
    "attack_speed": 192,
    "growth_speed": 223
  },
  {
    "id": 52,
    "ability_id": 1,
    "obtain_id": 1,
    "type_id": 1,
    "speed_id": 5,
    "size_id": 2,
    "temperature_id": 1,
    "ph_id": 1,
    "slug": "keburisu",
    "img": "https://raw.githubusercontent.com/takuyadev/kuriapi/main/assets/kin/face_sprite/kin_52.png",
    "hp": 146,
    "attack": 140,
    "defense": 13,
    "attack_speed": 45,
    "growth_speed": 130
  },
  {
    "id": 53,
    "ability_id": 1,
    "obtain_id": 1,
    "type_id": 1,
    "speed_id": 5,
    "size_id": 2,
    "temperature_id": 3,
    "ph_id": 1,
    "slug": "uzumakin",
    "img": "https://raw.githubusercontent.com/takuyadev/kuriapi/main/assets/kin/face_sprite/kin_53.png",
    "hp": 149,
    "attack": 138,
    "defense": 11,
    "attack_speed": 45,
    "growth_speed": 124
  },
  {
    "id": 54,
    "ability_id": 5,
    "obtain_id": 1,
    "type_id": 2,
    "speed_id": 5,
    "size_id": 2,
    "temperature_id": 1,
    "ph_id": 2,
    "slug": "furizun",
    "img": "https://raw.githubusercontent.com/takuyadev/kuriapi/main/assets/kin/face_sprite/kin_54.png",
    "hp": 152,
    "attack": 135,
    "defense": 8,
    "attack_speed": 40,
    "growth_speed": 137
  },
  {
    "id": 55,
    "ability_id": 3,
    "obtain_id": 1,
    "type_id": 3,
    "speed_id": 5,
    "size_id": 1,
    "temperature_id": 3,
    "ph_id": 1,
    "slug": "tokorokin",
    "img": "https://raw.githubusercontent.com/takuyadev/kuriapi/main/assets/kin/face_sprite/kin_55.png",
    "hp": 101,
    "attack": 28,
    "defense": 51,
    "attack_speed": 102,
    "growth_speed": 176
  },
  {
    "id": 56,
    "ability_id": 1,
    "obtain_id": 1,
    "type_id": 1,
    "speed_id": 5,
    "size_id": 2,
    "temperature_id": 2,
    "ph_id": 1,
    "slug": "jakkin",
    "img": "https://raw.githubusercontent.com/takuyadev/kuriapi/main/assets/kin/face_sprite/kin_56.png",
    "hp": 152,
    "attack": 135,
    "defense": 7,
    "attack_speed": 40,
    "growth_speed": 128
  },
  {
    "id": 57,
    "ability_id": 1,
    "obtain_id": 1,
    "type_id": 1,
    "speed_id": 5,
    "size_id": 2,
    "temperature_id": 1,
    "ph_id": 2,
    "slug": "haguruman",
    "img": "https://raw.githubusercontent.com/takuyadev/kuriapi/main/assets/kin/face_sprite/kin_57.png",
    "hp": 152,
    "attack": 135,
    "defense": 15,
    "attack_speed": 50,
    "growth_speed": 140
  },
  {
    "id": 58,
    "ability_id": 1,
    "obtain_id": 1,
    "type_id": 1,
    "speed_id": 5,
    "size_id": 2,
    "temperature_id": 1,
    "ph_id": 2,
    "slug": "muginia",
    "img": "https://raw.githubusercontent.com/takuyadev/kuriapi/main/assets/kin/face_sprite/kin_58.png",
    "hp": 152,
    "attack": 135,
    "defense": 24,
    "attack_speed": 35,
    "growth_speed": 123
  },
  {
    "id": 59,
    "ability_id": 2,
    "obtain_id": 1,
    "type_id": 2,
    "speed_id": 5,
    "size_id": 2,
    "temperature_id": 2,
    "ph_id": 2,
    "slug": "kasekin",
    "img": "https://raw.githubusercontent.com/takuyadev/kuriapi/main/assets/kin/face_sprite/kin_59.png",
    "hp": 152,
    "attack": 135,
    "defense": 3,
    "attack_speed": 35,
    "growth_speed": 138
  },
  {
    "id": 60,
    "ability_id": 2,
    "obtain_id": 1,
    "type_id": 2,
    "speed_id": 5,
    "size_id": 2,
    "temperature_id": 2,
    "ph_id": 2,
    "slug": "sakuria",
    "img": "https://raw.githubusercontent.com/takuyadev/kuriapi/main/assets/kin/face_sprite/kin_60.png",
    "hp": 152,
    "attack": 135,
    "defense": 23,
    "attack_speed": 27,
    "growth_speed": 120
  },
  {
    "id": 61,
    "ability_id": 2,
    "obtain_id": 1,
    "type_id": 2,
    "speed_id": 5,
    "size_id": 2,
    "temperature_id": 1,
    "ph_id": 1,
    "slug": "furasukosu",
    "img": "https://raw.githubusercontent.com/takuyadev/kuriapi/main/assets/kin/face_sprite/kin_61.png",
    "hp": 146,
    "attack": 140,
    "defense": 3,
    "attack_speed": 35,
    "growth_speed": 129
  },
  {
    "id": 62,
    "ability_id": 1,
    "obtain_id": 1,
    "type_id": 1,
    "speed_id": 5,
    "size_id": 2,
    "temperature_id": 3,
    "ph_id": 2,
    "slug": "mitokondoru",
    "img": "https://raw.githubusercontent.com/takuyadev/kuriapi/main/assets/kin/face_sprite/kin_62.png",
    "hp": 192,
    "attack": 95,
    "defense": 22,
    "attack_speed": 62,
    "growth_speed": 128
  },
  {
    "id": 63,
    "ability_id": 3,
    "obtain_id": 1,
    "type_id": 3,
    "speed_id": 5,
    "size_id": 1,
    "temperature_id": 2,
    "ph_id": 1,
    "slug": "misutima",
    "img": "https://raw.githubusercontent.com/takuyadev/kuriapi/main/assets/kin/face_sprite/kin_63.png",
    "hp": 79,
    "attack": 50,
    "defense": 1,
    "attack_speed": 62,
    "growth_speed": 220
  },
  {
    "id": 64,
    "ability_id": 5,
    "obtain_id": 1,
    "type_id": 3,
    "speed_id": 5,
    "size_id": 2,
    "temperature_id": 1,
    "ph_id": 1,
    "slug": "watagenomu",
    "img": "https://raw.githubusercontent.com/takuyadev/kuriapi/main/assets/kin/face_sprite/kin_64.png",
    "hp": 100,
    "attack": 186,
    "defense": 10,
    "attack_speed": 52,
    "growth_speed": 156
  },
  {
    "id": 65,
    "ability_id": 3,
    "obtain_id": 1,
    "type_id": 3,
    "speed_id": 5,
    "size_id": 2,
    "temperature_id": 1,
    "ph_id": 2,
    "slug": "hotaria",
    "img": "https://raw.githubusercontent.com/takuyadev/kuriapi/main/assets/kin/face_sprite/kin_65.png",
    "hp": 152,
    "attack": 135,
    "defense": 13,
    "attack_speed": 45,
    "growth_speed": 139
  },
  {
    "id": 66,
    "ability_id": 5,
    "obtain_id": 2,
    "type_id": 2,
    "speed_id": 5,
    "size_id": 2,
    "temperature_id": 3,
    "ph_id": 1,
    "slug": "kakaonian",
    "img": "https://raw.githubusercontent.com/takuyadev/kuriapi/main/assets/kin/face_sprite/kin_66.png",
    "hp": 146,
    "attack": 140,
    "defense": 16,
    "attack_speed": 50,
    "growth_speed": 127
  },
  {
    "id": 67,
    "ability_id": 4,
    "obtain_id": 2,
    "type_id": 3,
    "speed_id": 5,
    "size_id": 1,
    "temperature_id": 3,
    "ph_id": 1,
    "slug": "perorikin",
    "img": "https://raw.githubusercontent.com/takuyadev/kuriapi/main/assets/kin/face_sprite/kin_67.png",
    "hp": 75,
    "attack": 54,
    "defense": 16,
    "attack_speed": 72,
    "growth_speed": 221
  },
  {
    "id": 68,
    "ability_id": 4,
    "obtain_id": 2,
    "type_id": 1,
    "speed_id": 5,
    "size_id": 2,
    "temperature_id": 3,
    "ph_id": 2,
    "slug": "daioukin",
    "img": "https://raw.githubusercontent.com/takuyadev/kuriapi/main/assets/kin/face_sprite/kin_68.png",
    "hp": 152,
    "attack": 135,
    "defense": 33,
    "attack_speed": 55,
    "growth_speed": 126
  },
  {
    "id": 69,
    "ability_id": 6,
    "obtain_id": 2,
    "type_id": 3,
    "speed_id": 5,
    "size_id": 1,
    "temperature_id": 3,
    "ph_id": 1,
    "slug": "kouteipenkin",
    "img": "https://raw.githubusercontent.com/takuyadev/kuriapi/main/assets/kin/face_sprite/kin_69.png",
    "hp": 76,
    "attack": 53,
    "defense": 16,
    "attack_speed": 62,
    "growth_speed": 215
  },
  {
    "id": 70,
    "ability_id": 4,
    "obtain_id": 2,
    "type_id": 2,
    "speed_id": 5,
    "size_id": 2,
    "temperature_id": 3,
    "ph_id": 1,
    "slug": "hekusarianzu",
    "img": "https://raw.githubusercontent.com/takuyadev/kuriapi/main/assets/kin/face_sprite/kin_70.png",
    "hp": 152,
    "attack": 135,
    "defense": 21,
    "attack_speed": 45,
    "growth_speed": 124
  },
  {
    "id": 71,
    "ability_id": 5,
    "obtain_id": 2,
    "type_id": 2,
    "speed_id": 5,
    "size_id": 1,
    "temperature_id": 1,
    "ph_id": 2,
    "slug": "hakkaku",
    "img": "https://raw.githubusercontent.com/takuyadev/kuriapi/main/assets/kin/face_sprite/kin_71.png",
    "hp": 81,
    "attack": 48,
    "defense": 70,
    "attack_speed": 112,
    "growth_speed": 153
  },
  {
    "id": 72,
    "ability_id": 7,
    "obtain_id": 2,
    "type_id": 2,
    "speed_id": 5,
    "size_id": 2,
    "temperature_id": 3,
    "ph_id": 2,
    "slug": "magunaria",
    "img": "https://raw.githubusercontent.com/takuyadev/kuriapi/main/assets/kin/face_sprite/kin_72.png",
    "hp": 92,
    "attack": 195,
    "defense": 17,
    "attack_speed": 35,
    "growth_speed": 129
  },
  {
    "id": 73,
    "ability_id": 6,
    "obtain_id": 2,
    "type_id": 2,
    "speed_id": 3,
    "size_id": 3,
    "temperature_id": 3,
    "ph_id": 1,
    "slug": "kurisutaria",
    "img": "https://raw.githubusercontent.com/takuyadev/kuriapi/main/assets/kin/face_sprite/kin_73.png",
    "hp": 227,
    "attack": 218,
    "defense": 25,
    "attack_speed": 13,
    "growth_speed": 48
  },
  {
    "id": 74,
    "ability_id": 6,
    "obtain_id": 2,
    "type_id": 2,
    "speed_id": 3,
    "size_id": 3,
    "temperature_id": 1,
    "ph_id": 1,
    "slug": "warusutaria",
    "img": "https://raw.githubusercontent.com/takuyadev/kuriapi/main/assets/kin/face_sprite/kin_74.png",
    "hp": 355,
    "attack": 89,
    "defense": 16,
    "attack_speed": 7,
    "growth_speed": 5
  },
  {
    "id": 75,
    "ability_id": 6,
    "obtain_id": 2,
    "type_id": 2,
    "speed_id": 3,
    "size_id": 3,
    "temperature_id": 2,
    "ph_id": 1,
    "slug": "metarudotto",
    "img": "https://raw.githubusercontent.com/takuyadev/kuriapi/main/assets/kin/face_sprite/kin_75.png",
    "hp": 227,
    "attack": 218,
    "defense": 15,
    "attack_speed": 15,
    "growth_speed": 48
  },
  {
    "id": 76,
    "ability_id": 4,
    "obtain_id": 2,
    "type_id": 2,
    "speed_id": 3,
    "size_id": 3,
    "temperature_id": 1,
    "ph_id": 1,
    "slug": "kuragen",
    "img": "https://raw.githubusercontent.com/takuyadev/kuriapi/main/assets/kin/face_sprite/kin_76.png",
    "hp": 227,
    "attack": 218,
    "defense": 10,
    "attack_speed": 14,
    "growth_speed": 49
  },
  {
    "id": 77,
    "ability_id": 6,
    "obtain_id": 2,
    "type_id": 1,
    "speed_id": 5,
    "size_id": 2,
    "temperature_id": 3,
    "ph_id": 1,
    "slug": "shiomanekin",
    "img": "https://raw.githubusercontent.com/takuyadev/kuriapi/main/assets/kin/face_sprite/kin_77.png",
    "hp": 89,
    "attack": 198,
    "defense": 23,
    "attack_speed": 35,
    "growth_speed": 122
  },
  {
    "id": 78,
    "ability_id": 4,
    "obtain_id": 2,
    "type_id": 3,
    "speed_id": 5,
    "size_id": 1,
    "temperature_id": 1,
    "ph_id": 2,
    "slug": "gosutokin",
    "img": "https://raw.githubusercontent.com/takuyadev/kuriapi/main/assets/kin/face_sprite/kin_78.png",
    "hp": 75,
    "attack": 54,
    "defense": 26,
    "attack_speed": 77,
    "growth_speed": 225
  },
  {
    "id": 79,
    "ability_id": 5,
    "obtain_id": 2,
    "type_id": 2,
    "speed_id": 5,
    "size_id": 2,
    "temperature_id": 3,
    "ph_id": 1,
    "slug": "haniwamu",
    "img": "https://raw.githubusercontent.com/takuyadev/kuriapi/main/assets/kin/face_sprite/kin_79.png",
    "hp": 152,
    "attack": 135,
    "defense": 23,
    "attack_speed": 35,
    "growth_speed": 124
  },
  {
    "id": 80,
    "ability_id": 6,
    "obtain_id": 2,
    "type_id": 3,
    "speed_id": 5,
    "size_id": 1,
    "temperature_id": 3,
    "ph_id": 1,
    "slug": "sukuriumu",
    "img": "https://raw.githubusercontent.com/takuyadev/kuriapi/main/assets/kin/face_sprite/kin_80.png",
    "hp": 75,
    "attack": 54,
    "defense": 18,
    "attack_speed": 72,
    "growth_speed": 220
  },
  {
    "id": 81,
    "ability_id": 7,
    "obtain_id": 2,
    "type_id": 3,
    "speed_id": 5,
    "size_id": 2,
    "temperature_id": 1,
    "ph_id": 2,
    "slug": "ekusutoriumu",
    "img": "https://raw.githubusercontent.com/takuyadev/kuriapi/main/assets/kin/face_sprite/kin_81.png",
    "hp": 100,
    "attack": 186,
    "defense": 11,
    "attack_speed": 45,
    "growth_speed": 145
  },
  {
    "id": 82,
    "ability_id": 5,
    "obtain_id": 2,
    "type_id": 2,
    "speed_id": 5,
    "size_id": 1,
    "temperature_id": 2,
    "ph_id": 1,
    "slug": "sukarkin",
    "img": "https://raw.githubusercontent.com/takuyadev/kuriapi/main/assets/kin/face_sprite/kin_82.png",
    "hp": 41,
    "attack": 88,
    "defense": 2,
    "attack_speed": 82,
    "growth_speed": 237
  },
  {
    "id": 83,
    "ability_id": 5,
    "obtain_id": 2,
    "type_id": 1,
    "speed_id": 5,
    "size_id": 1,
    "temperature_id": 1,
    "ph_id": 1,
    "slug": "sodosuta",
    "img": "https://raw.githubusercontent.com/takuyadev/kuriapi/main/assets/kin/face_sprite/kin_83.png",
    "hp": 84,
    "attack": 45,
    "defense": 32,
    "attack_speed": 57,
    "growth_speed": 205
  },
  {
    "id": 84,
    "ability_id": 4,
    "obtain_id": 2,
    "type_id": 2,
    "speed_id": 5,
    "size_id": 2,
    "temperature_id": 1,
    "ph_id": 1,
    "slug": "bunshimogei",
    "img": "https://raw.githubusercontent.com/takuyadev/kuriapi/main/assets/kin/face_sprite/kin_84.png",
    "hp": 152,
    "attack": 135,
    "defense": 2,
    "attack_speed": 45,
    "growth_speed": 140
  },
  {
    "id": 85,
    "ability_id": 6,
    "obtain_id": 2,
    "type_id": 1,
    "speed_id": 5,
    "size_id": 2,
    "temperature_id": 1,
    "ph_id": 1,
    "slug": "bananaifu",
    "img": "https://raw.githubusercontent.com/takuyadev/kuriapi/main/assets/kin/face_sprite/kin_85.png",
    "hp": 152,
    "attack": 135,
    "defense": 1,
    "attack_speed": 35,
    "growth_speed": 130
  },
  {
    "id": 86,
    "ability_id": 6,
    "obtain_id": 2,
    "type_id": 3,
    "speed_id": 5,
    "size_id": 2,
    "temperature_id": 2,
    "ph_id": 2,
    "slug": "yubuin",
    "img": "https://raw.githubusercontent.com/takuyadev/kuriapi/main/assets/kin/face_sprite/kin_86.png",
    "hp": 195,
    "attack": 92,
    "defense": 22,
    "attack_speed": 62,
    "growth_speed": 128
  },
  {
    "id": 87,
    "ability_id": 6,
    "obtain_id": 2,
    "type_id": 3,
    "speed_id": 5,
    "size_id": 2,
    "temperature_id": 3,
    "ph_id": 1,
    "slug": "bakuterin",
    "img": "https://raw.githubusercontent.com/takuyadev/kuriapi/main/assets/kin/face_sprite/kin_87.png",
    "hp": 43,
    "attack": 244,
    "defense": 2,
    "attack_speed": 222,
    "growth_speed": 228
  },
  {
    "id": 88,
    "ability_id": 5,
    "obtain_id": 2,
    "type_id": 1,
    "speed_id": 5,
    "size_id": 2,
    "temperature_id": 3,
    "ph_id": 1,
    "slug": "jasuteria",
    "img": "https://raw.githubusercontent.com/takuyadev/kuriapi/main/assets/kin/face_sprite/kin_88.png",
    "hp": 115,
    "attack": 172,
    "defense": 12,
    "attack_speed": 22,
    "growth_speed": 94
  },
  {
    "id": 89,
    "ability_id": 4,
    "obtain_id": 2,
    "type_id": 1,
    "speed_id": 3,
    "size_id": 3,
    "temperature_id": 2,
    "ph_id": 1,
    "slug": "puragu",
    "img": "https://raw.githubusercontent.com/takuyadev/kuriapi/main/assets/kin/face_sprite/kin_89.png",
    "hp": 227,
    "attack": 218,
    "defense": 15,
    "attack_speed": 15,
    "growth_speed": 70
  },
  {
    "id": 90,
    "ability_id": 5,
    "obtain_id": 2,
    "type_id": 1,
    "speed_id": 5,
    "size_id": 1,
    "temperature_id": 1,
    "ph_id": 2,
    "slug": "baikingu",
    "img": "https://raw.githubusercontent.com/takuyadev/kuriapi/main/assets/kin/face_sprite/kin_90.png",
    "hp": 74,
    "attack": 55,
    "defense": 40,
    "attack_speed": 82,
    "growth_speed": 224
  },
  {
    "id": 91,
    "ability_id": 5,
    "obtain_id": 2,
    "type_id": 1,
    "speed_id": 5,
    "size_id": 2,
    "temperature_id": 2,
    "ph_id": 1,
    "slug": "ingenkin",
    "img": "https://raw.githubusercontent.com/takuyadev/kuriapi/main/assets/kin/face_sprite/kin_91.png",
    "hp": 152,
    "attack": 135,
    "defense": 8,
    "attack_speed": 40,
    "growth_speed": 141
  },
  {
    "id": 92,
    "ability_id": 5,
    "obtain_id": 2,
    "type_id": 3,
    "speed_id": 3,
    "size_id": 3,
    "temperature_id": 3,
    "ph_id": 1,
    "slug": "piyorikin",
    "img": "https://raw.githubusercontent.com/takuyadev/kuriapi/main/assets/kin/face_sprite/kin_92.png",
    "hp": 227,
    "attack": 218,
    "defense": 33,
    "attack_speed": 15,
    "growth_speed": 49
  },
  {
    "id": 93,
    "ability_id": 5,
    "obtain_id": 2,
    "type_id": 3,
    "speed_id": 3,
    "size_id": 3,
    "temperature_id": 3,
    "ph_id": 2,
    "slug": "yotsubakin",
    "img": "https://raw.githubusercontent.com/takuyadev/kuriapi/main/assets/kin/face_sprite/kin_93.png",
    "hp": 227,
    "attack": 218,
    "defense": 5,
    "attack_speed": 13,
    "growth_speed": 58
  },
  {
    "id": 94,
    "ability_id": 4,
    "obtain_id": 2,
    "type_id": 3,
    "speed_id": 3,
    "size_id": 3,
    "temperature_id": 2,
    "ph_id": 1,
    "slug": "asunaria",
    "img": "https://raw.githubusercontent.com/takuyadev/kuriapi/main/assets/kin/face_sprite/kin_94.png",
    "hp": 200,
    "attack": 244,
    "defense": 33,
    "attack_speed": 7,
    "growth_speed": 4
  },
  {
    "id": 95,
    "ability_id": 6,
    "obtain_id": 2,
    "type_id": 1,
    "speed_id": 3,
    "size_id": 3,
    "temperature_id": 3,
    "ph_id": 2,
    "slug": "barasaito",
    "img": "https://raw.githubusercontent.com/takuyadev/kuriapi/main/assets/kin/face_sprite/kin_95.png",
    "hp": 267,
    "attack": 178,
    "defense": 31,
    "attack_speed": 20,
    "growth_speed": 73
  },
  {
    "id": 96,
    "ability_id": 5,
    "obtain_id": 2,
    "type_id": 1,
    "speed_id": 5,
    "size_id": 1,
    "temperature_id": 1,
    "ph_id": 1,
    "slug": "debirusu",
    "img": "https://raw.githubusercontent.com/takuyadev/kuriapi/main/assets/kin/face_sprite/kin_96.png",
    "hp": 67,
    "attack": 62,
    "defense": 5,
    "attack_speed": 57,
    "growth_speed": 220
  },
  {
    "id": 97,
    "ability_id": 6,
    "obtain_id": 2,
    "type_id": 1,
    "speed_id": 5,
    "size_id": 3,
    "temperature_id": 1,
    "ph_id": 1,
    "slug": "sutingura",
    "img": "https://raw.githubusercontent.com/takuyadev/kuriapi/main/assets/kin/face_sprite/kin_97.png",
    "hp": 227,
    "attack": 218,
    "defense": 10,
    "attack_speed": 32,
    "growth_speed": 1
  },
  {
    "id": 98,
    "ability_id": 4,
    "obtain_id": 2,
    "type_id": 3,
    "speed_id": 4,
    "size_id": 2,
    "temperature_id": 2,
    "ph_id": 2,
    "slug": "aroman",
    "img": "https://raw.githubusercontent.com/takuyadev/kuriapi/main/assets/kin/face_sprite/kin_98.png",
    "hp": 57,
    "attack": 229,
    "defense": 13,
    "attack_speed": 45,
    "growth_speed": 129
  },
  {
    "id": 99,
    "ability_id": 5,
    "obtain_id": 2,
    "type_id": 1,
    "speed_id": 5,
    "size_id": 2,
    "temperature_id": 2,
    "ph_id": 1,
    "slug": "piramia",
    "img": "https://raw.githubusercontent.com/takuyadev/kuriapi/main/assets/kin/face_sprite/kin_99.png",
    "hp": 92,
    "attack": 195,
    "defense": 22,
    "attack_speed": 35,
    "growth_speed": 126
  },
  {
    "id": 100,
    "ability_id": 5,
    "obtain_id": 2,
    "type_id": 1,
    "speed_id": 4,
    "size_id": 3,
    "temperature_id": 2,
    "ph_id": 1,
    "slug": "daburerekin",
    "img": "https://raw.githubusercontent.com/takuyadev/kuriapi/main/assets/kin/face_sprite/kin_100.png",
    "hp": 200,
    "attack": 244,
    "defense": 1,
    "attack_speed": 15,
    "growth_speed": 6
  },
  {
    "id": 101,
    "ability_id": 7,
    "obtain_id": 2,
    "type_id": 1,
    "speed_id": 5,
    "size_id": 2,
    "temperature_id": 2,
    "ph_id": 1,
    "slug": "ponkotsuburikin",
    "img": "https://raw.githubusercontent.com/takuyadev/kuriapi/main/assets/kin/face_sprite/kin_101.png",
    "hp": 152,
    "attack": 135,
    "defense": 6,
    "attack_speed": 35,
    "growth_speed": 131
  },
  {
    "id": 102,
    "ability_id": 5,
    "obtain_id": 2,
    "type_id": 2,
    "speed_id": 5,
    "size_id": 2,
    "temperature_id": 2,
    "ph_id": 1,
    "slug": "bukkumakin",
    "img": "https://raw.githubusercontent.com/takuyadev/kuriapi/main/assets/kin/face_sprite/kin_102.png",
    "hp": 149,
    "attack": 138,
    "defense": 6,
    "attack_speed": 40,
    "growth_speed": 127
  },
  {
    "id": 103,
    "ability_id": 5,
    "obtain_id": 2,
    "type_id": 1,
    "speed_id": 5,
    "size_id": 2,
    "temperature_id": 2,
    "ph_id": 2,
    "slug": "kurobi",
    "img": "https://raw.githubusercontent.com/takuyadev/kuriapi/main/assets/kin/face_sprite/kin_103.png",
    "hp": 152,
    "attack": 135,
    "defense": 22,
    "attack_speed": 27,
    "growth_speed": 120
  },
  {
    "id": 104,
    "ability_id": 7,
    "obtain_id": 2,
    "type_id": 2,
    "speed_id": 5,
    "size_id": 1,
    "temperature_id": 3,
    "ph_id": 1,
    "slug": "charanpowan",
    "img": "https://raw.githubusercontent.com/takuyadev/kuriapi/main/assets/kin/face_sprite/kin_104.png",
    "hp": 77,
    "attack": 52,
    "defense": 44,
    "attack_speed": 82,
    "growth_speed": 226
  },
  {
    "id": 105,
    "ability_id": 4,
    "obtain_id": 2,
    "type_id": 1,
    "speed_id": 5,
    "size_id": 1,
    "temperature_id": 3,
    "ph_id": 2,
    "slug": "bakuterinus",
    "img": "https://raw.githubusercontent.com/takuyadev/kuriapi/main/assets/kin/face_sprite/kin_105.png",
    "hp": 75,
    "attack": 54,
    "defense": 25,
    "attack_speed": 77,
    "growth_speed": 215
  },
  {
    "id": 106,
    "ability_id": 5,
    "obtain_id": 2,
    "type_id": 3,
    "speed_id": 5,
    "size_id": 2,
    "temperature_id": 3,
    "ph_id": 1,
    "slug": "sarunerakin",
    "img": "https://raw.githubusercontent.com/takuyadev/kuriapi/main/assets/kin/face_sprite/kin_106.png",
    "hp": 175,
    "attack": 112,
    "defense": 7,
    "attack_speed": 40,
    "growth_speed": 124
  },
  {
    "id": 107,
    "ability_id": 6,
    "obtain_id": 2,
    "type_id": 2,
    "speed_id": 5,
    "size_id": 2,
    "temperature_id": 2,
    "ph_id": 1,
    "slug": "pandaberu",
    "img": "https://raw.githubusercontent.com/takuyadev/kuriapi/main/assets/kin/face_sprite/kin_107.png",
    "hp": 146,
    "attack": 140,
    "defense": 20,
    "attack_speed": 55,
    "growth_speed": 131
  },
  {
    "id": 108,
    "ability_id": 5,
    "obtain_id": 2,
    "type_id": 3,
    "speed_id": 5,
    "size_id": 1,
    "temperature_id": 3,
    "ph_id": 1,
    "slug": "koronekin",
    "img": "https://raw.githubusercontent.com/takuyadev/kuriapi/main/assets/kin/face_sprite/kin_108.png",
    "hp": 76,
    "attack": 53,
    "defense": 33,
    "attack_speed": 82,
    "growth_speed": 214
  },
  {
    "id": 109,
    "ability_id": 6,
    "obtain_id": 2,
    "type_id": 3,
    "speed_id": 4,
    "size_id": 2,
    "temperature_id": 1,
    "ph_id": 1,
    "slug": "purofiria",
    "img": "https://raw.githubusercontent.com/takuyadev/kuriapi/main/assets/kin/face_sprite/kin_109.png",
    "hp": 215,
    "attack": 72,
    "defense": 63,
    "attack_speed": 92,
    "growth_speed": 35
  },
  {
    "id": 110,
    "ability_id": 6,
    "obtain_id": 2,
    "type_id": 1,
    "speed_id": 4,
    "size_id": 2,
    "temperature_id": 3,
    "ph_id": 1,
    "slug": "kinobugoddo",
    "img": "https://raw.githubusercontent.com/takuyadev/kuriapi/main/assets/kin/face_sprite/kin_110.png",
    "hp": 92,
    "attack": 195,
    "defense": 1,
    "attack_speed": 74,
    "growth_speed": 240
  },
  {
    "id": 111,
    "ability_id": 1,
    "obtain_id": 3,
    "type_id": 1,
    "speed_id": 5,
    "size_id": 2,
    "temperature_id": 2,
    "ph_id": 1,
    "slug": "mayuhando",
    "img": "https://raw.githubusercontent.com/takuyadev/kuriapi/main/assets/kin/face_sprite/kin_111.png",
    "hp": 152,
    "attack": 135,
    "defense": 12,
    "attack_speed": 55,
    "growth_speed": 141
  },
  {
    "id": 112,
    "ability_id": 3,
    "obtain_id": 3,
    "type_id": 3,
    "speed_id": 5,
    "size_id": 1,
    "temperature_id": 1,
    "ph_id": 1,
    "slug": "mokumone",
    "img": "https://raw.githubusercontent.com/takuyadev/kuriapi/main/assets/kin/face_sprite/kin_112.png",
    "hp": 77,
    "attack": 52,
    "defense": 19,
    "attack_speed": 82,
    "growth_speed": 235
  },
  {
    "id": 113,
    "ability_id": 2,
    "obtain_id": 3,
    "type_id": 2,
    "speed_id": 5,
    "size_id": 2,
    "temperature_id": 1,
    "ph_id": 1,
    "slug": "kureyonisu",
    "img": "https://raw.githubusercontent.com/takuyadev/kuriapi/main/assets/kin/face_sprite/kin_113.png",
    "hp": 149,
    "attack": 138,
    "defense": 12,
    "attack_speed": 45,
    "growth_speed": 137
  },
  {
    "id": 114,
    "ability_id": 3,
    "obtain_id": 3,
    "type_id": 3,
    "speed_id": 5,
    "size_id": 1,
    "temperature_id": 2,
    "ph_id": 1,
    "slug": "zukin",
    "img": "https://raw.githubusercontent.com/takuyadev/kuriapi/main/assets/kin/face_sprite/kin_114.png",
    "hp": 74,
    "attack": 55,
    "defense": 13,
    "attack_speed": 72,
    "growth_speed": 234
  },
  {
    "id": 115,
    "ability_id": 1,
    "obtain_id": 3,
    "type_id": 1,
    "speed_id": 5,
    "size_id": 1,
    "temperature_id": 1,
    "ph_id": 2,
    "slug": "bitorunaits",
    "img": "https://raw.githubusercontent.com/takuyadev/kuriapi/main/assets/kin/face_sprite/kin_115.png",
    "hp": 75,
    "attack": 54,
    "defense": 24,
    "attack_speed": 77,
    "growth_speed": 235
  },
  {
    "id": 116,
    "ability_id": 1,
    "obtain_id": 3,
    "type_id": 2,
    "speed_id": 5,
    "size_id": 2,
    "temperature_id": 1,
    "ph_id": 2,
    "slug": "harinezukin",
    "img": "https://raw.githubusercontent.com/takuyadev/kuriapi/main/assets/kin/face_sprite/kin_116.png",
    "hp": 146,
    "attack": 140,
    "defense": 12,
    "attack_speed": 35,
    "growth_speed": 134
  },
  {
    "id": 117,
    "ability_id": 3,
    "obtain_id": 3,
    "type_id": 3,
    "speed_id": 5,
    "size_id": 2,
    "temperature_id": 1,
    "ph_id": 1,
    "slug": "tanukin",
    "img": "https://raw.githubusercontent.com/takuyadev/kuriapi/main/assets/kin/face_sprite/kin_117.png",
    "hp": 146,
    "attack": 140,
    "defense": 22,
    "attack_speed": 55,
    "growth_speed": 132
  },
  {
    "id": 118,
    "ability_id": 3,
    "obtain_id": 3,
    "type_id": 3,
    "speed_id": 5,
    "size_id": 2,
    "temperature_id": 2,
    "ph_id": 1,
    "slug": "piconyanko",
    "img": "https://raw.githubusercontent.com/takuyadev/kuriapi/main/assets/kin/face_sprite/kin_118.png",
    "hp": 152,
    "attack": 135,
    "defense": 14,
    "attack_speed": 45,
    "growth_speed": 140
  },
  {
    "id": 119,
    "ability_id": 2,
    "obtain_id": 3,
    "type_id": 2,
    "speed_id": 5,
    "size_id": 2,
    "temperature_id": 2,
    "ph_id": 1,
    "slug": "mikurofangu",
    "img": "https://raw.githubusercontent.com/takuyadev/kuriapi/main/assets/kin/face_sprite/kin_119.png",
    "hp": 146,
    "attack": 140,
    "defense": 14,
    "attack_speed": 35,
    "growth_speed": 137
  },
  {
    "id": 120,
    "ability_id": 3,
    "obtain_id": 3,
    "type_id": 3,
    "speed_id": 5,
    "size_id": 2,
    "temperature_id": 1,
    "ph_id": 1,
    "slug": "tefutefupapi",
    "img": "https://raw.githubusercontent.com/takuyadev/kuriapi/main/assets/kin/face_sprite/kin_120.png",
    "hp": 146,
    "attack": 140,
    "defense": 21,
    "attack_speed": 55,
    "growth_speed": 139
  },
  {
    "id": 121,
    "ability_id": 1,
    "obtain_id": 3,
    "type_id": 1,
    "speed_id": 5,
    "size_id": 2,
    "temperature_id": 2,
    "ph_id": 1,
    "slug": "koakumania",
    "img": "https://raw.githubusercontent.com/takuyadev/kuriapi/main/assets/kin/face_sprite/kin_121.png",
    "hp": 149,
    "attack": 138,
    "defense": 13,
    "attack_speed": 35,
    "growth_speed": 135
  },
  {
    "id": 122,
    "ability_id": 1,
    "obtain_id": 3,
    "type_id": 1,
    "speed_id": 5,
    "size_id": 2,
    "temperature_id": 3,
    "ph_id": 1,
    "slug": "doragofaji",
    "img": "https://raw.githubusercontent.com/takuyadev/kuriapi/main/assets/kin/face_sprite/kin_122.png",
    "hp": 146,
    "attack": 140,
    "defense": 16,
    "attack_speed": 40,
    "growth_speed": 135
  },
  {
    "id": 123,
    "ability_id": 2,
    "obtain_id": 3,
    "type_id": 2,
    "speed_id": 5,
    "size_id": 1,
    "temperature_id": 2,
    "ph_id": 1,
    "slug": "kururibashi",
    "img": "https://raw.githubusercontent.com/takuyadev/kuriapi/main/assets/kin/face_sprite/kin_123.png",
    "hp": 76,
    "attack": 53,
    "defense": 13,
    "attack_speed": 62,
    "growth_speed": 223
  },
  {
    "id": 124,
    "ability_id": 2,
    "obtain_id": 3,
    "type_id": 2,
    "speed_id": 5,
    "size_id": 1,
    "temperature_id": 2,
    "ph_id": 1,
    "slug": "adamusukin",
    "img": "https://raw.githubusercontent.com/takuyadev/kuriapi/main/assets/kin/face_sprite/kin_124.png",
    "hp": 79,
    "attack": 50,
    "defense": 34,
    "attack_speed": 82,
    "growth_speed": 235
  },
  {
    "id": 125,
    "ability_id": 2,
    "obtain_id": 3,
    "type_id": 2,
    "speed_id": 5,
    "size_id": 2,
    "temperature_id": 3,
    "ph_id": 1,
    "slug": "runasutein",
    "img": "https://raw.githubusercontent.com/takuyadev/kuriapi/main/assets/kin/face_sprite/kin_125.png",
    "hp": 146,
    "attack": 140,
    "defense": 18,
    "attack_speed": 50,
    "growth_speed": 133
  },
  {
    "id": 126,
    "ability_id": 6,
    "obtain_id": 4,
    "type_id": 3,
    "speed_id": 5,
    "size_id": 1,
    "temperature_id": 2,
    "ph_id": 1,
    "slug": "kekin",
    "img": "https://raw.githubusercontent.com/takuyadev/kuriapi/main/assets/kin/face_sprite/kin_126.png",
    "hp": 41,
    "attack": 88,
    "defense": 2,
    "attack_speed": 77,
    "growth_speed": 254
  },
  {
    "id": 127,
    "ability_id": 6,
    "obtain_id": 4,
    "type_id": 1,
    "speed_id": 5,
    "size_id": 2,
    "temperature_id": 2,
    "ph_id": 1,
    "slug": "otamaji",
    "img": "https://raw.githubusercontent.com/takuyadev/kuriapi/main/assets/kin/face_sprite/kin_127.png",
    "hp": 152,
    "attack": 135,
    "defense": 21,
    "attack_speed": 55,
    "growth_speed": 124
  },
  {
    "id": 128,
    "ability_id": 7,
    "obtain_id": 4,
    "type_id": 2,
    "speed_id": 2,
    "size_id": 3,
    "temperature_id": 3,
    "ph_id": 1,
    "slug": "gunkamakin",
    "img": "https://raw.githubusercontent.com/takuyadev/kuriapi/main/assets/kin/face_sprite/kin_128.png",
    "hp": 227,
    "attack": 218,
    "defense": 82,
    "attack_speed": 17,
    "growth_speed": 1
  }
 ]